FW/CPLD/basicfunctions/Parallel2Serial.v
//Parallel2Serial.v
//Convert the parallel data into serial data (12bits)
//

`define ADC_CHIP_NO 4
`define SPI_CLK_NO 20+(12*`ADC_CHIP_NO*2)
module Parallel2Serial (

	//clock in: 24Mhz clk
    input clkin,
	 
	 //enable the logic, pulse signal
	 input enable,
	
	 //parallel data and control signal
	 input [11:0] db, //data[11:0]
    output reg [`ADC_CHIP_NO-1:0] cs_bar, //chip select to ad
	 output reg rd_bar,//read signal to ad

	 
//    //serial port
    output reg sclk,
//    input miso,
    output reg mosi);
	 
	 
	 reg [3:0] sel;
	 reg [6:0] cnter;
	 reg en;
	 reg enspi;
	 reg [`ADC_CHIP_NO-1:0] reg_cs_bar;
	 reg [11:0] dbreg;
	 reg dbrdy;
	 		
	 initial begin
			sel <= 4'b0;
			cnter <= 6'h00;
			en <= 1'b0;
			sclk <= 1'b1;
			rd_bar <= 1'b1;
			reg_cs_bar <= `ADC_CHIP_NO'b00;
			dbrdy <= 1'b0;
			cs_bar <= 4'b1111;
			mosi <= 1'b0;
	 end
	 
	 
	 always @(clkin) begin
		 
		 if(clkin == 1'b1) begin
			 if(enable == 1'b1) begin
				 en = 1'b1;
			 end
			 
			 // stop the enable signal after 
			 // counter count to some value
			 if(cnter == 6'd`SPI_CLK_NO) begin
				 en = 1'b0;
				 cnter = 6'h0;
			 end
			 
			 //During en signal:
			 // counter add up
			 // generate the rd cs signal
			 if(en == 1'b1) begin
				 cnter = cnter + 6'h1;
				 
				 //when the counter is one
				 //generate the rd signal
				 if((cnter == 7'h1)|
					(cnter == 7'h1b)|
					(cnter == 7'h35)|
					(cnter == 7'h4f))
				 begin
					rd_bar = 1'b0;
				 end
				 if((cnter == 7'h3)|
					(cnter == 7'h1d)|
					(cnter == 7'h37)|
					(cnter == 7'h51))
				 begin
					rd_bar = 1'b1;
				 end
			end
			
			//control the enspi signal
			if((cnter == 7'h1c)|
				(cnter == 7'h36)|
				(cnter == 7'h50)|
				(cnter == 7'h6A))
			 begin
				enspi = 1'b0;
			 end
		end
		else begin
			//read the parallel data
			if(rd_bar == 1'b0) begin
				dbrdy = 1'b1;
			end
			else begin
				dbrdy = 1'b0;
				
			end
			//control the enspi signal
			if((cnter == 7'h3)|
				(cnter == 7'h1d)|
				(cnter == 7'h37)|
				(cnter == 7'h51))
			 begin
				enspi = 1'b1;
			 end
			
		end
	 end
	 
	 
	 //generate the cs signal 
	 always @(rd_bar) begin
		 if(rd_bar == 1'b0) begin
			reg_cs_bar = reg_cs_bar << 1;
			if(reg_cs_bar == `ADC_CHIP_NO'b0) begin
				reg_cs_bar = `ADC_CHIP_NO'b1;
			end 
			cs_bar = ~reg_cs_bar;
		 end
		 else begin
			cs_bar = ~`ADC_CHIP_NO'b0;
		 end
	 end
	 
	 //sample the data
	 always @(posedge clkin) begin
		if((dbrdy == 1'b1)&(rd_bar == 1'b0)) begin
			dbreg <= db;		
		end 
	 end
	 


    //convert parallel data into serial
	 //dbrdy negedge work as a enable signal to spi

	 
	 always @(posedge clkin) begin
	  
			if(enspi == 1'b1) begin
				sclk = ~sclk;
				//read the data into register
            if(sclk == 1'b0) begin
                mosi = dbreg[sel];
            end
            else begin
                sel = sel + 1;
            end
			end
			
			//check the sel value
			if(sel == 4'b1100) begin
				sel = 4'b0000;
			end
	  end
	 
endmodule

FW/CPLD/basicfunctions/ad7864Drv.v
//AD7864 CPLD Driver 
//CPLD code read the AD7864 all four channel adc data
//The driver in this version generate the necessary signals
//to communicate with AD7864 in internal clk mode.
// The driver is based on timing-diagram in ad7864 datasheet REV.D page 16

module ad7864Drv 
//#( parameter ADC_CHIP_NO = 4 )
(

    //clock in
    input clkin, 
	 //input pin from dsp
    //convert signal from dsp, this signal start everything
    input dsp_conv_bar, //dsp-->
   
    
    //convert signal to ad7865
	 output clkout, //clk to adc
    output ad_conv_bar, //-->ad
	 output reg db_rdy


);

    reg [6:0] cnter; //counter for clkin
	 reg adcen;
	 reg clken;

	 
	 
	 //initialize the regs
	 initial begin
		cnter <= 6'b000000;
		adcen <= 1'b0;
		clken <= 1'b0;
		db_rdy <= 1'b0;
	 end
		
    assign ad_conv_bar = dsp_conv_bar;
	 
	 
	 //set adc enable signal
	 always @(clkin) begin
		if (clkin == 1'b1) begin
			if(dsp_conv_bar == 1'b0) 
				begin
					cnter <= 6'b00000;
					adcen <= 1'b1;
				end
			else
				begin
					cnter <= cnter + 1;
				end
				
			//begin the adc clock
			if(adcen == 1'b1) begin 
				if((cnter == 6'h03))
					begin
						clken <= 1'b1;
					end		
				
				//here should read the data
				if(cnter == 6'h11)
					begin
						db_rdy <= 1'b1;
					end
				if(cnter == 6'h12)
					begin
						db_rdy <= 1'b0;
					end				
				if(cnter == 6'h3b)
					begin
						adcen <= 1'b0;
					end
			 end
		 end
	end
	
	//clk out to adc
	assign clkout = clkin && adcen && clken;

endmodule

FW/CPLD/basicfunctions/testbench.v
`timescale 100ns/10ns

//TestBench for AD7864
// iverilog -g2005-sv -o testbench ad7864Drv.v testbench.v
module testbench;
    reg clki;
	 reg clkihf;
    reg conv2;
    reg conv;
    reg rd;
    reg [3:0] cs;
    reg [11:0] datas;
    wire spi_clk, spi_miso, spi_mosi;



    ad7864Drv DUT1(.clkin(clki),
		  .clkout(clko),
        .dsp_conv_bar(conv),
        .ad_conv_bar(conv2),
		  .db_rdy(en));
		  
	 Parallel2Serial DUT2(.clkin(clkihf),
			.enable(en),
			.db(datas),
			.cs_bar(cs),
			.rd_bar(rd));

        reg [1:0] cnter;
    
    initial begin
        $dumpfile("testbench.vcd");$dumpvars(0,testbench);
        $monitor($time, "conv = %b, clki = %b", conv,clki);
        clki = 1'b0;
		  clkihf = 1'b0;
        conv = 1'b1;
        datas = 11'b10111010010;
 
    end

    always begin
        #8 clki = ~clki;
	 end
	 
	 always begin
	     #1 clkihf = ~clkihf;
	 end
    

    initial begin
        #2000 $finish;
    end
    
    always begin
        #1000 conv = 1'b0;
        #16 conv = 1'b1;
    end
	 
	 always begin
		#50 datas = datas + 11'b1;
	 end
    
endmodule

FW/CPLD/basicfunctions/testbench.vcd
$date
	Sun Sep 19 21:44:55 2021
$end
$version
	Icarus Verilog
$end
$timescale
	10ns
$end
$scope module testbench $end
$var wire 1 ! rd $end
$var wire 1 " en $end
$var wire 4 # cs [3:0] $end
$var wire 1 $ conv2 $end
$var wire 1 % clko $end
$var reg 1 & clki $end
$var reg 1 ' clkihf $end
$var reg 1 ( conv $end
$var reg 12 ) datas [11:0] $end
$scope module DUT1 $end
$var wire 1 $ ad_conv_bar $end
$var wire 1 & clkin $end
$var wire 1 % clkout $end
$var wire 1 ( dsp_conv_bar $end
$var reg 1 * adcen $end
$var reg 1 + clken $end
$var reg 7 , cnter [6:0] $end
$var reg 1 " db_rdy $end
$upscope $end
$scope module DUT2 $end
$var wire 1 ' clkin $end
$var wire 12 - db [11:0] $end
$var wire 1 " enable $end
$var reg 7 . cnter [6:0] $end
$var reg 4 / cs_bar [3:0] $end
$var reg 1 0 dbrdy $end
$var reg 12 1 dbreg [11:0] $end
$var reg 1 2 en $end
$var reg 1 3 enspi $end
$var reg 1 4 mosi $end
$var reg 1 ! rd_bar $end
$var reg 4 5 reg_cs_bar [3:0] $end
$var reg 1 6 sclk $end
$var reg 4 7 sel [3:0] $end
$upscope $end
$upscope $end
$enddefinitions $end
#0
$dumpvars
b0 7
16
b0 5
04
x3
02
bx 1
00
b1111 /
b0 .
b10111010010 -
b0 ,
0+
0*
b10111010010 )
1(
0'
0&
0%
1$
b1111 #
0"
1!
$end
#10
1'
#20
0'
#30
1'
#40
0'
#50
1'
#60
0'
#70
1'
#80
b1 ,
0'
1&
#90
1'
#100
0'
#110
1'
#120
0'
#130
1'
#140
0'
#150
1'
#160
0'
0&
#170
1'
#180
0'
#190
1'
#200
0'
#210
1'
#220
0'
#230
1'
#240
b10 ,
0'
1&
#250
1'
#260
0'
#270
1'
#280
0'
#290
1'
#300
0'
#310
1'
#320
0'
0&
#330
1'
#340
0'
#350
1'
#360
0'
#370
1'
#380
0'
#390
1'
#400
b11 ,
0'
1&
#410
1'
#420
0'
#430
1'
#440
0'
#450
1'
#460
0'
#470
1'
#480
0'
0&
#490
1'
#500
0'
b10111010011 )
b10111010011 -
#510
1'
#520
0'
#530
1'
#540
0'
#550
1'
#560
b100 ,
0'
1&
#570
1'
#580
0'
#590
1'
#600
0'
#610
1'
#620
0'
#630
1'
#640
0'
0&
#650
1'
#660
0'
#670
1'
#680
0'
#690
1'
#700
0'
#710
1'
#720
b101 ,
0'
1&
#730
1'
#740
0'
#750
1'
#760
0'
#770
1'
#780
0'
#790
1'
#800
0'
0&
#810
1'
#820
0'
#830
1'
#840
0'
#850
1'
#860
0'
#870
1'
#880
b110 ,
0'
1&
#890
1'
#900
0'
#910
1'
#920
0'
#930
1'
#940
0'
#950
1'
#960
0'
0&
#970
1'
#980
0'
#990
1'
#1000
0'
b10111010100 )
b10111010100 -
#1010
1'
#1020
0'
#1030
1'
#1040
b111 ,
0'
1&
#1050
1'
#1060
0'
#1070
1'
#1080
0'
#1090
1'
#1100
0'
#1110
1'
#1120
0'
0&
#1130
1'
#1140
0'
#1150
1'
#1160
0'
#1170
1'
#1180
0'
#1190
1'
#1200
b1000 ,
0'
1&
#1210
1'
#1220
0'
#1230
1'
#1240
0'
#1250
1'
#1260
0'
#1270
1'
#1280
0'
0&
#1290
1'
#1300
0'
#1310
1'
#1320
0'
#1330
1'
#1340
0'
#1350
1'
#1360
b1001 ,
0'
1&
#1370
1'
#1380
0'
#1390
1'
#1400
0'
#1410
1'
#1420
0'
#1430
1'
#1440
0'
0&
#1450
1'
#1460
0'
#1470
1'
#1480
0'
#1490
1'
#1500
0'
b10111010101 )
b10111010101 -
#1510
1'
#1520
b1010 ,
0'
1&
#1530
1'
#1540
0'
#1550
1'
#1560
0'
#1570
1'
#1580
0'
#1590
1'
#1600
0'
0&
#1610
1'
#1620
0'
#1630
1'
#1640
0'
#1650
1'
#1660
0'
#1670
1'
#1680
b1011 ,
0'
1&
#1690
1'
#1700
0'
#1710
1'
#1720
0'
#1730
1'
#1740
0'
#1750
1'
#1760
0'
0&
#1770
1'
#1780
0'
#1790
1'
#1800
0'
#1810
1'
#1820
0'
#1830
1'
#1840
b1100 ,
0'
1&
#1850
1'
#1860
0'
#1870
1'
#1880
0'
#1890
1'
#1900
0'
#1910
1'
#1920
0'
0&
#1930
1'
#1940
0'
#1950
1'
#1960
0'
#1970
1'
#1980
0'
#1990
1'
#2000
b1101 ,
0'
1&
b10111010110 )
b10111010110 -
#2010
1'
#2020
0'
#2030
1'
#2040
0'
#2050
1'
#2060
0'
#2070
1'
#2080
0'
0&
#2090
1'
#2100
0'
#2110
1'
#2120
0'
#2130
1'
#2140
0'
#2150
1'
#2160
b1110 ,
0'
1&
#2170
1'
#2180
0'
#2190
1'
#2200
0'
#2210
1'
#2220
0'
#2230
1'
#2240
0'
0&
#2250
1'
#2260
0'
#2270
1'
#2280
0'
#2290
1'
#2300
0'
#2310
1'
#2320
b1111 ,
0'
1&
#2330
1'
#2340
0'
#2350
1'
#2360
0'
#2370
1'
#2380
0'
#2390
1'
#2400
0'
0&
#2410
1'
#2420
0'
#2430
1'
#2440
0'
#2450
1'
#2460
0'
#2470
1'
#2480
b10000 ,
0'
1&
#2490
1'
#2500
0'
b10111010111 )
b10111010111 -
#2510
1'
#2520
0'
#2530
1'
#2540
0'
#2550
1'
#2560
0'
0&
#2570
1'
#2580
0'
#2590
1'
#2600
0'
#2610
1'
#2620
0'
#2630
1'
#2640
b10001 ,
0'
1&
#2650
1'
#2660
0'
#2670
1'
#2680
0'
#2690
1'
#2700
0'
#2710
1'
#2720
0'
0&
#2730
1'
#2740
0'
#2750
1'
#2760
0'
#2770
1'
#2780
0'
#2790
1'
#2800
b10010 ,
0'
1&
#2810
1'
#2820
0'
#2830
1'
#2840
0'
#2850
1'
#2860
0'
#2870
1'
#2880
0'
0&
#2890
1'
#2900
0'
#2910
1'
#2920
0'
#2930
1'
#2940
0'
#2950
1'
#2960
b10011 ,
0'
1&
#2970
1'
#2980
0'
#2990
1'
#3000
0'
b10111011000 )
b10111011000 -
#3010
1'
#3020
0'
#3030
1'
#3040
0'
0&
#3050
1'
#3060
0'
#3070
1'
#3080
0'
#3090
1'
#3100
0'
#3110
1'
#3120
b10100 ,
0'
1&
#3130
1'
#3140
0'
#3150
1'
#3160
0'
#3170
1'
#3180
0'
#3190
1'
#3200
0'
0&
#3210
1'
#3220
0'
#3230
1'
#3240
0'
#3250
1'
#3260
0'
#3270
1'
#3280
b10101 ,
0'
1&
#3290
1'
#3300
0'
#3310
1'
#3320
0'
#3330
1'
#3340
0'
#3350
1'
#3360
0'
0&
#3370
1'
#3380
0'
#3390
1'
#3400
0'
#3410
1'
#3420
0'
#3430
1'
#3440
b10110 ,
0'
1&
#3450
1'
#3460
0'
#3470
1'
#3480
0'
#3490
1'
#3500
0'
b10111011001 )
b10111011001 -
#3510
1'
#3520
0'
0&
#3530
1'
#3540
0'
#3550
1'
#3560
0'
#3570
1'
#3580
0'
#3590
1'
#3600
b10111 ,
0'
1&
#3610
1'
#3620
0'
#3630
1'
#3640
0'
#3650
1'
#3660
0'
#3670
1'
#3680
0'
0&
#3690
1'
#3700
0'
#3710
1'
#3720
0'
#3730
1'
#3740
0'
#3750
1'
#3760
b11000 ,
0'
1&
#3770
1'
#3780
0'
#3790
1'
#3800
0'
#3810
1'
#3820
0'
#3830
1'
#3840
0'
0&
#3850
1'
#3860
0'
#3870
1'
#3880
0'
#3890
1'
#3900
0'
#3910
1'
#3920
b11001 ,
0'
1&
#3930
1'
#3940
0'
#3950
1'
#3960
0'
#3970
1'
#3980
0'
#3990
1'
#4000
0'
0&
b10111011010 )
b10111011010 -
#4010
1'
#4020
0'
#4030
1'
#4040
0'
#4050
1'
#4060
0'
#4070
1'
#4080
b11010 ,
0'
1&
#4090
1'
#4100
0'
#4110
1'
#4120
0'
#4130
1'
#4140
0'
#4150
1'
#4160
0'
0&
#4170
1'
#4180
0'
#4190
1'
#4200
0'
#4210
1'
#4220
0'
#4230
1'
#4240
b11011 ,
0'
1&
#4250
1'
#4260
0'
#4270
1'
#4280
0'
#4290
1'
#4300
0'
#4310
1'
#4320
0'
0&
#4330
1'
#4340
0'
#4350
1'
#4360
0'
#4370
1'
#4380
0'
#4390
1'
#4400
b11100 ,
0'
1&
#4410
1'
#4420
0'
#4430
1'
#4440
0'
#4450
1'
#4460
0'
#4470
1'
#4480
0'
0&
#4490
1'
#4500
0'
b10111011011 )
b10111011011 -
#4510
1'
#4520
0'
#4530
1'
#4540
0'
#4550
1'
#4560
b11101 ,
0'
1&
#4570
1'
#4580
0'
#4590
1'
#4600
0'
#4610
1'
#4620
0'
#4630
1'
#4640
0'
0&
#4650
1'
#4660
0'
#4670
1'
#4680
0'
#4690
1'
#4700
0'
#4710
1'
#4720
b11110 ,
0'
1&
#4730
1'
#4740
0'
#4750
1'
#4760
0'
#4770
1'
#4780
0'
#4790
1'
#4800
0'
0&
#4810
1'
#4820
0'
#4830
1'
#4840
0'
#4850
1'
#4860
0'
#4870
1'
#4880
b11111 ,
0'
1&
#4890
1'
#4900
0'
#4910
1'
#4920
0'
#4930
1'
#4940
0'
#4950
1'
#4960
0'
0&
#4970
1'
#4980
0'
#4990
1'
#5000
0'
b10111011100 )
b10111011100 -
#5010
1'
#5020
0'
#5030
1'
#5040
b100000 ,
0'
1&
#5050
1'
#5060
0'
#5070
1'
#5080
0'
#5090
1'
#5100
0'
#5110
1'
#5120
0'
0&
#5130
1'
#5140
0'
#5150
1'
#5160
0'
#5170
1'
#5180
0'
#5190
1'
#5200
b100001 ,
0'
1&
#5210
1'
#5220
0'
#5230
1'
#5240
0'
#5250
1'
#5260
0'
#5270
1'
#5280
0'
0&
#5290
1'
#5300
0'
#5310
1'
#5320
0'
#5330
1'
#5340
0'
#5350
1'
#5360
b100010 ,
0'
1&
#5370
1'
#5380
0'
#5390
1'
#5400
0'
#5410
1'
#5420
0'
#5430
1'
#5440
0'
0&
#5450
1'
#5460
0'
#5470
1'
#5480
0'
#5490
1'
#5500
0'
b10111011101 )
b10111011101 -
#5510
1'
#5520
b100011 ,
0'
1&
#5530
1'
#5540
0'
#5550
1'
#5560
0'
#5570
1'
#5580
0'
#5590
1'
#5600
0'
0&
#5610
1'
#5620
0'
#5630
1'
#5640
0'
#5650
1'
#5660
0'
#5670
1'
#5680
b100100 ,
0'
1&
#5690
1'
#5700
0'
#5710
1'
#5720
0'
#5730
1'
#5740
0'
#5750
1'
#5760
0'
0&
#5770
1'
#5780
0'
#5790
1'
#5800
0'
#5810
1'
#5820
0'
#5830
1'
#5840
b100101 ,
0'
1&
#5850
1'
#5860
0'
#5870
1'
#5880
0'
#5890
1'
#5900
0'
#5910
1'
#5920
0'
0&
#5930
1'
#5940
0'
#5950
1'
#5960
0'
#5970
1'
#5980
0'
#5990
1'
#6000
b100110 ,
0'
1&
b10111011110 )
b10111011110 -
#6010
1'
#6020
0'
#6030
1'
#6040
0'
#6050
1'
#6060
0'
#6070
1'
#6080
0'
0&
#6090
1'
#6100
0'
#6110
1'
#6120
0'
#6130
1'
#6140
0'
#6150
1'
#6160
b100111 ,
0'
1&
#6170
1'
#6180
0'
#6190
1'
#6200
0'
#6210
1'
#6220
0'
#6230
1'
#6240
0'
0&
#6250
1'
#6260
0'
#6270
1'
#6280
0'
#6290
1'
#6300
0'
#6310
1'
#6320
b101000 ,
0'
1&
#6330
1'
#6340
0'
#6350
1'
#6360
0'
#6370
1'
#6380
0'
#6390
1'
#6400
0'
0&
#6410
1'
#6420
0'
#6430
1'
#6440
0'
#6450
1'
#6460
0'
#6470
1'
#6480
b101001 ,
0'
1&
#6490
1'
#6500
0'
b10111011111 )
b10111011111 -
#6510
1'
#6520
0'
#6530
1'
#6540
0'
#6550
1'
#6560
0'
0&
#6570
1'
#6580
0'
#6590
1'
#6600
0'
#6610
1'
#6620
0'
#6630
1'
#6640
b101010 ,
0'
1&
#6650
1'
#6660
0'
#6670
1'
#6680
0'
#6690
1'
#6700
0'
#6710
1'
#6720
0'
0&
#6730
1'
#6740
0'
#6750
1'
#6760
0'
#6770
1'
#6780
0'
#6790
1'
#6800
b101011 ,
0'
1&
#6810
1'
#6820
0'
#6830
1'
#6840
0'
#6850
1'
#6860
0'
#6870
1'
#6880
0'
0&
#6890
1'
#6900
0'
#6910
1'
#6920
0'
#6930
1'
#6940
0'
#6950
1'
#6960
b101100 ,
0'
1&
#6970
1'
#6980
0'
#6990
1'
#7000
0'
b10111100000 )
b10111100000 -
#7010
1'
#7020
0'
#7030
1'
#7040
0'
0&
#7050
1'
#7060
0'
#7070
1'
#7080
0'
#7090
1'
#7100
0'
#7110
1'
#7120
b101101 ,
0'
1&
#7130
1'
#7140
0'
#7150
1'
#7160
0'
#7170
1'
#7180
0'
#7190
1'
#7200
0'
0&
#7210
1'
#7220
0'
#7230
1'
#7240
0'
#7250
1'
#7260
0'
#7270
1'
#7280
b101110 ,
0'
1&
#7290
1'
#7300
0'
#7310
1'
#7320
0'
#7330
1'
#7340
0'
#7350
1'
#7360
0'
0&
#7370
1'
#7380
0'
#7390
1'
#7400
0'
#7410
1'
#7420
0'
#7430
1'
#7440
b101111 ,
0'
1&
#7450
1'
#7460
0'
#7470
1'
#7480
0'
#7490
1'
#7500
0'
b10111100001 )
b10111100001 -
#7510
1'
#7520
0'
0&
#7530
1'
#7540
0'
#7550
1'
#7560
0'
#7570
1'
#7580
0'
#7590
1'
#7600
b110000 ,
0'
1&
#7610
1'
#7620
0'
#7630
1'
#7640
0'
#7650
1'
#7660
0'
#7670
1'
#7680
0'
0&
#7690
1'
#7700
0'
#7710
1'
#7720
0'
#7730
1'
#7740
0'
#7750
1'
#7760
b110001 ,
0'
1&
#7770
1'
#7780
0'
#7790
1'
#7800
0'
#7810
1'
#7820
0'
#7830
1'
#7840
0'
0&
#7850
1'
#7860
0'
#7870
1'
#7880
0'
#7890
1'
#7900
0'
#7910
1'
#7920
b110010 ,
0'
1&
#7930
1'
#7940
0'
#7950
1'
#7960
0'
#7970
1'
#7980
0'
#7990
1'
#8000
0'
0&
b10111100010 )
b10111100010 -
#8010
1'
#8020
0'
#8030
1'
#8040
0'
#8050
1'
#8060
0'
#8070
1'
#8080
b110011 ,
0'
1&
#8090
1'
#8100
0'
#8110
1'
#8120
0'
#8130
1'
#8140
0'
#8150
1'
#8160
0'
0&
#8170
1'
#8180
0'
#8190
1'
#8200
0'
#8210
1'
#8220
0'
#8230
1'
#8240
b110100 ,
0'
1&
#8250
1'
#8260
0'
#8270
1'
#8280
0'
#8290
1'
#8300
0'
#8310
1'
#8320
0'
0&
#8330
1'
#8340
0'
#8350
1'
#8360
0'
#8370
1'
#8380
0'
#8390
1'
#8400
b110101 ,
0'
1&
#8410
1'
#8420
0'
#8430
1'
#8440
0'
#8450
1'
#8460
0'
#8470
1'
#8480
0'
0&
#8490
1'
#8500
0'
b10111100011 )
b10111100011 -
#8510
1'
#8520
0'
#8530
1'
#8540
0'
#8550
1'
#8560
b110110 ,
0'
1&
#8570
1'
#8580
0'
#8590
1'
#8600
0'
#8610
1'
#8620
0'
#8630
1'
#8640
0'
0&
#8650
1'
#8660
0'
#8670
1'
#8680
0'
#8690
1'
#8700
0'
#8710
1'
#8720
b110111 ,
0'
1&
#8730
1'
#8740
0'
#8750
1'
#8760
0'
#8770
1'
#8780
0'
#8790
1'
#8800
0'
0&
#8810
1'
#8820
0'
#8830
1'
#8840
0'
#8850
1'
#8860
0'
#8870
1'
#8880
b111000 ,
0'
1&
#8890
1'
#8900
0'
#8910
1'
#8920
0'
#8930
1'
#8940
0'
#8950
1'
#8960
0'
0&
#8970
1'
#8980
0'
#8990
1'
#9000
0'
b10111100100 )
b10111100100 -
#9010
1'
#9020
0'
#9030
1'
#9040
b111001 ,
0'
1&
#9050
1'
#9060
0'
#9070
1'
#9080
0'
#9090
1'
#9100
0'
#9110
1'
#9120
0'
0&
#9130
1'
#9140
0'
#9150
1'
#9160
0'
#9170
1'
#9180
0'
#9190
1'
#9200
b111010 ,
0'
1&
#9210
1'
#9220
0'
#9230
1'
#9240
0'
#9250
1'
#9260
0'
#9270
1'
#9280
0'
0&
#9290
1'
#9300
0'
#9310
1'
#9320
0'
#9330
1'
#9340
0'
#9350
1'
#9360
b111011 ,
0'
1&
#9370
1'
#9380
0'
#9390
1'
#9400
0'
#9410
1'
#9420
0'
#9430
1'
#9440
0'
0&
#9450
1'
#9460
0'
#9470
1'
#9480
0'
#9490
1'
#9500
0'
b10111100101 )
b10111100101 -
#9510
1'
#9520
b111100 ,
0'
1&
#9530
1'
#9540
0'
#9550
1'
#9560
0'
#9570
1'
#9580
0'
#9590
1'
#9600
0'
0&
#9610
1'
#9620
0'
#9630
1'
#9640
0'
#9650
1'
#9660
0'
#9670
1'
#9680
b111101 ,
0'
1&
#9690
1'
#9700
0'
#9710
1'
#9720
0'
#9730
1'
#9740
0'
#9750
1'
#9760
0'
0&
#9770
1'
#9780
0'
#9790
1'
#9800
0'
#9810
1'
#9820
0'
#9830
1'
#9840
b111110 ,
0'
1&
#9850
1'
#9860
0'
#9870
1'
#9880
0'
#9890
1'
#9900
0'
#9910
1'
#9920
0'
0&
#9930
1'
#9940
0'
#9950
1'
#9960
0'
#9970
1'
#9980
0'
#9990
1'
#10000
1*
b0 ,
0'
1&
b10111100110 )
b10111100110 -
0$
0(
#10010
1'
#10020
0'
#10030
1'
#10040
0'
#10050
1'
#10060
0'
#10070
1'
#10080
0'
0&
#10090
1'
#10100
0'
#10110
1'
#10120
0'
#10130
1'
#10140
0'
#10150
1'
#10160
b1 ,
0'
1&
1$
1(
#10170
1'
#10180
0'
#10190
1'
#10200
0'
#10210
1'
#10220
0'
#10230
1'
#10240
0'
0&
#10250
1'
#10260
0'
#10270
1'
#10280
0'
#10290
1'
#10300
0'
#10310
1'
#10320
b10 ,
0'
1&
#10330
1'
#10340
0'
#10350
1'
#10360
0'
#10370
1'
#10380
0'
#10390
1'
#10400
0'
0&
#10410
1'
#10420
0'
#10430
1'
#10440
0'
#10450
1'
#10460
0'
#10470
1'
#10480
b11 ,
0'
1&
#10490
1'
#10500
0'
b10111100111 )
b10111100111 -
#10510
1'
#10520
0'
#10530
1'
#10540
0'
#10550
1'
#10560
0'
0&
#10570
1'
#10580
0'
#10590
1'
#10600
0'
#10610
1'
#10620
0'
#10630
1'
#10640
1%
1+
b100 ,
0'
1&
#10650
1'
#10660
0'
#10670
1'
#10680
0'
#10690
1'
#10700
0'
#10710
1'
#10720
0%
0'
0&
#10730
1'
#10740
0'
#10750
1'
#10760
0'
#10770
1'
#10780
0'
#10790
1'
#10800
b101 ,
1%
0'
1&
#10810
1'
#10820
0'
#10830
1'
#10840
0'
#10850
1'
#10860
0'
#10870
1'
#10880
0%
0'
0&
#10890
1'
#10900
0'
#10910
1'
#10920
0'
#10930
1'
#10940
0'
#10950
1'
#10960
b110 ,
1%
0'
1&
#10970
1'
#10980
0'
#10990
1'
#11000
0'
b10111101000 )
b10111101000 -
#11010
1'
#11020
0'
#11030
1'
#11040
0%
0'
0&
#11050
1'
#11060
0'
#11070
1'
#11080
0'
#11090
1'
#11100
0'
#11110
1'
#11120
b111 ,
1%
0'
1&
#11130
1'
#11140
0'
#11150
1'
#11160
0'
#11170
1'
#11180
0'
#11190
1'
#11200
0%
0'
0&
#11210
1'
#11220
0'
#11230
1'
#11240
0'
#11250
1'
#11260
0'
#11270
1'
#11280
b1000 ,
1%
0'
1&
#11290
1'
#11300
0'
#11310
1'
#11320
0'
#11330
1'
#11340
0'
#11350
1'
#11360
0%
0'
0&
#11370
1'
#11380
0'
#11390
1'
#11400
0'
#11410
1'
#11420
0'
#11430
1'
#11440
b1001 ,
1%
0'
1&
#11450
1'
#11460
0'
#11470
1'
#11480
0'
#11490
1'
#11500
0'
b10111101001 )
b10111101001 -
#11510
1'
#11520
0%
0'
0&
#11530
1'
#11540
0'
#11550
1'
#11560
0'
#11570
1'
#11580
0'
#11590
1'
#11600
b1010 ,
1%
0'
1&
#11610
1'
#11620
0'
#11630
1'
#11640
0'
#11650
1'
#11660
0'
#11670
1'
#11680
0%
0'
0&
#11690
1'
#11700
0'
#11710
1'
#11720
0'
#11730
1'
#11740
0'
#11750
1'
#11760
b1011 ,
1%
0'
1&
#11770
1'
#11780
0'
#11790
1'
#11800
0'
#11810
1'
#11820
0'
#11830
1'
#11840
0%
0'
0&
#11850
1'
#11860
0'
#11870
1'
#11880
0'
#11890
1'
#11900
0'
#11910
1'
#11920
b1100 ,
1%
0'
1&
#11930
1'
#11940
0'
#11950
1'
#11960
0'
#11970
1'
#11980
0'
#11990
1'
#12000
0%
0'
0&
b10111101010 )
b10111101010 -
#12010
1'
#12020
0'
#12030
1'
#12040
0'
#12050
1'
#12060
0'
#12070
1'
#12080
b1101 ,
1%
0'
1&
#12090
1'
#12100
0'
#12110
1'
#12120
0'
#12130
1'
#12140
0'
#12150
1'
#12160
0%
0'
0&
#12170
1'
#12180
0'
#12190
1'
#12200
0'
#12210
1'
#12220
0'
#12230
1'
#12240
b1110 ,
1%
0'
1&
#12250
1'
#12260
0'
#12270
1'
#12280
0'
#12290
1'
#12300
0'
#12310
1'
#12320
0%
0'
0&
#12330
1'
#12340
0'
#12350
1'
#12360
0'
#12370
1'
#12380
0'
#12390
1'
#12400
b1111 ,
1%
0'
1&
#12410
1'
#12420
0'
#12430
1'
#12440
0'
#12450
1'
#12460
0'
#12470
1'
#12480
0%
0'
0&
#12490
1'
#12500
0'
b10111101011 )
b10111101011 -
#12510
1'
#12520
0'
#12530
1'
#12540
0'
#12550
1'
#12560
b10000 ,
1%
0'
1&
#12570
1'
#12580
0'
#12590
1'
#12600
0'
#12610
1'
#12620
0'
#12630
1'
#12640
0%
0'
0&
#12650
1'
#12660
0'
#12670
1'
#12680
0'
#12690
1'
#12700
0'
#12710
1'
#12720
b10001 ,
1%
0'
1&
#12730
1'
#12740
0'
#12750
1'
#12760
0'
#12770
1'
#12780
0'
#12790
1'
#12800
0%
0'
0&
#12810
1'
#12820
0'
#12830
1'
#12840
0'
#12850
1'
#12860
0'
#12870
1'
#12880
1"
b10010 ,
1%
0'
1&
#12890
b1110 #
b1110 /
b1 5
0!
b1 .
12
1'
#12900
10
0'
#12910
b10111101011 1
b10 .
1'
#12920
0'
#12930
b1111 #
b1111 /
1!
b11 .
1'
#12940
13
00
0'
#12950
14
06
b100 .
1'
#12960
0%
0'
0&
#12970
b1 7
16
b101 .
1'
#12980
0'
#12990
06
b110 .
1'
#13000
0'
b10111101100 )
b10111101100 -
#13010
b10 7
16
b111 .
1'
#13020
0'
#13030
04
06
b1000 .
1'
#13040
0"
b10011 ,
1%
0'
1&
#13050
b11 7
16
b1001 .
1'
#13060
0'
#13070
14
06
b1010 .
1'
#13080
0'
#13090
b100 7
16
b1011 .
1'
#13100
0'
#13110
04
06
b1100 .
1'
#13120
0%
0'
0&
#13130
b101 7
16
b1101 .
1'
#13140
0'
#13150
14
06
b1110 .
1'
#13160
0'
#13170
b110 7
16
b1111 .
1'
#13180
0'
#13190
06
b10000 .
1'
#13200
b10100 ,
1%
0'
1&
#13210
b111 7
16
b10001 .
1'
#13220
0'
#13230
06
b10010 .
1'
#13240
0'
#13250
b1000 7
16
b10011 .
1'
#13260
0'
#13270
06
b10100 .
1'
#13280
0%
0'
0&
#13290
b1001 7
16
b10101 .
1'
#13300
0'
#13310
04
06
b10110 .
1'
#13320
0'
#13330
b1010 7
16
b10111 .
1'
#13340
0'
#13350
14
06
b11000 .
1'
#13360
b10101 ,
1%
0'
1&
