FW/CPLD/basicfunctions/ad7864Drv.v
//AD7864 CPLD Driver 
//CPLD code read the AD7864 all four channel adc data
//And convert the parallel data into serial data
//The driver in this version generate the necessary signals
//to communicate with AD7864 in internal clk mode.
// The driver is based on timing-diagram in ad7864 datasheet REV.D page 16


module ad7864Drv (

    //clock in
    input clkin, 
	 //input pin from dsp
    //convert signal from dsp, this signal start everything
    input dsp_conv_bar, //dsp-->
	 
    
    
    //convert signal to ad7865
	 output clkout, //clk to adc
    output ad_conv_bar, //-->ad
    output reg rd_bar, //read signal to ad
    output cs_bar, //chip select to ad
    input [11:0] db, //data[11:0]

    //serial port
    output reg sclk,
    input miso,
    output reg mosi

);

    reg db_rdy; //data ready signal
    reg [6:0] cnter; //counter for clkin
    reg [11:0] db_reg;
    reg [4:0] sel;
	 reg adcen;
	 reg clken;
	 
	 
	 //initialize the regs
	 initial begin
		cnter <= 6'b000000;
		adcen <= 1'b0;
		rd_bar <= 1'b1;
		clken <= 1'b0;
	 end
		
    assign ad_conv_bar = dsp_conv_bar;
	 
	 
	 //set adc enable signal
	 always @(clkin) begin
		if (clkin == 1'b1) begin
			if(dsp_conv_bar == 1'b0) 
				begin
					cnter <= 6'b00000;
					adcen <= 1'b1;
				end
			else
				begin
					cnter <= cnter + 1;
				end
				
			//begin the adc clock
			if(adcen == 1'b1) begin 
				if((cnter == 6'h03))
					begin
						clken <= 1'b1;
					end		
				
				//here should read the data
				if((cnter == 6'h11)|(cnter == 6'h1F)|(cnter == 6'h2D)|(cnter == 6'h3B))
					begin
						db_rdy <= 1'b1;
					end
					
					
				if(cnter == 6'h3f)
					begin
						adcen <= 1'b0;
					end
			 end
		 end
	 else begin
		if(adcen == 1'b1) begin
			if((cnter == 6'h10)|(cnter == 6'h1E)|(cnter == 6'h2C)|(cnter == 6'h3A))
				begin
					rd_bar <= 1'b0;
				end
			if((cnter == 6'h11)|(cnter == 6'h1F)|(cnter == 6'h2D)|(cnter == 6'h3B))
				begin
					rd_bar <= 1'b1;
				end
			end
	 end
	end
	 
	 
	 assign cs_bar  = rd_bar;
	 
	 
	 
	 assign clkout = clkin && adcen && clken;
	 
	 
    //convert paralle data into serial
    always @(posedge clkin) begin
        //read the data into register
        if(db_rdy == 1'b1) begin
            db_reg <= db;
            //read the data into register
            sclk = ~sclk;
            if(sclk == 1'b0) begin
                mosi = db_reg[sel];
            end
            else begin
                sel = sel + 1;
            end
        end
        else begin
            sclk <= 1'b0;
            mosi <= 1'b0;
            sel <= 4'b0000;
        end       
    end




endmodule

FW/CPLD/testbench.v
`timescale 100ns/10ns
//TestBench for AD7864
module testbench;
    reg clki;
    reg conv2;
    reg conv;
    reg rd;
    reg cs;
    reg [11:0] datas;
    wire spi_clk, spi_miso, spi_mosi;



    ad7864Drv DUT(.clkin(clki),
		  .clkout(clko),
        .dsp_conv_bar(conv),
        .ad_conv_bar(conv2),
        .rd_bar(rd),
        .cs_bar(cs),
        .db(datas),
        .sclk(spi_clk),
        .miso(spi_miso),
        .mosi(spi_mosi) );

        reg [1:0] cnter;
    
    initial begin
        $dumpfile("testbench.vcd");$dumpvars(0,testbench);
        $monitor($time, "conv = %b, clki = %b", conv,clki);
        clki = 1'b0;
        conv = 1'b1;
        datas = 11'b10111010010;
 
    end

    always
        #1 clki = ~clki;
    

    initial begin
        #700 $finish;
    end
    
    always begin
        #240 conv = 1'b0;
        #2 conv = 1'b1;
    end
    
endmodule

FW/CPLD/basicfunctions/testbench.vcd
$date
	Mon Aug 30 23:12:00 2021
$end
$version
	Icarus Verilog
$end
$timescale
	10ns
$end
$scope module testbench $end
$var wire 1 ! spi_mosi $end
$var wire 1 " spi_miso $end
$var wire 1 # spi_clk $end
$var wire 1 $ rd $end
$var wire 1 % cs $end
$var wire 1 & conv2 $end
$var wire 1 ' clko $end
$var reg 1 ( clki $end
$var reg 1 ) conv $end
$var reg 12 * datas [11:0] $end
$scope module DUT $end
$var wire 1 & ad_conv_bar $end
$var wire 1 ( clkin $end
$var wire 1 ' clkout $end
$var wire 1 % cs_bar $end
$var wire 12 + db [11:0] $end
$var wire 1 ) dsp_conv_bar $end
$var reg 1 , adcen $end
$var reg 1 - clken $end
$var reg 7 . cnter [6:0] $end
$var reg 1 / db_rdy $end
$var reg 12 0 db_reg [11:0] $end
$var reg 1 " miso $end
$var reg 1 ! mosi $end
$var reg 1 $ rd_bar $end
$var reg 1 # sclk $end
$var reg 5 1 sel [4:0] $end
$upscope $end
$upscope $end
$enddefinitions $end
#0
$dumpvars
bx 1
bx 0
x/
b0 .
0-
0,
b10111010010 +
b10111010010 *
1)
0(
0'
1&
1%
1$
x#
x"
x!
$end
#10
b0 1
0!
0#
b1 .
1(
#20
0(
#30
b10 .
1(
#40
0(
#50
b11 .
1(
#60
0(
#70
b100 .
1(
#80
0(
#90
b101 .
1(
#100
0(
#110
b110 .
1(
#120
0(
#130
b111 .
1(
#140
0(
#150
b1000 .
1(
#160
0(
#170
b1001 .
1(
#180
0(
#190
b1010 .
1(
#200
0(
#210
b1011 .
1(
#220
0(
#230
b1100 .
1(
#240
0(
#250
b1101 .
1(
#260
0(
#270
b1110 .
1(
#280
0(
#290
b1111 .
1(
#300
0(
#310
b10000 .
1(
#320
0(
#330
b10001 .
1(
#340
0(
#350
b10010 .
1(
#360
0(
#370
b10011 .
1(
#380
0(
#390
b10100 .
1(
#400
0(
#410
b10101 .
1(
#420
0(
#430
b10110 .
1(
#440
0(
#450
b10111 .
1(
#460
0(
#470
b11000 .
1(
#480
0(
#490
b11001 .
1(
#500
0(
#510
b11010 .
1(
#520
0(
#530
b11011 .
1(
#540
0(
#550
b11100 .
1(
#560
0(
#570
b11101 .
1(
#580
0(
#590
b11110 .
1(
#600
0(
#610
b11111 .
1(
#620
0(
#630
b100000 .
1(
#640
0(
#650
b100001 .
1(
#660
0(
#670
b100010 .
1(
#680
0(
#690
b100011 .
1(
#700
0(
#710
b100100 .
1(
#720
0(
#730
b100101 .
1(
#740
0(
#750
b100110 .
1(
#760
0(
#770
b100111 .
1(
#780
0(
#790
b101000 .
1(
#800
0(
#810
b101001 .
1(
#820
0(
#830
b101010 .
1(
#840
0(
#850
b101011 .
1(
#860
0(
#870
b101100 .
1(
#880
0(
#890
b101101 .
1(
#900
0(
#910
b101110 .
1(
#920
0(
#930
b101111 .
1(
#940
0(
#950
b110000 .
1(
#960
0(
#970
b110001 .
1(
#980
0(
#990
b110010 .
1(
#1000
0(
#1010
b110011 .
1(
#1020
0(
#1030
b110100 .
1(
#1040
0(
#1050
b110101 .
1(
#1060
0(
#1070
b110110 .
1(
#1080
0(
#1090
b110111 .
1(
#1100
0(
#1110
b111000 .
1(
#1120
0(
#1130
b111001 .
1(
#1140
0(
#1150
b111010 .
1(
#1160
0(
#1170
b111011 .
1(
#1180
0(
#1190
b111100 .
1(
#1200
0(
#1210
b111101 .
1(
#1220
0(
#1230
b111110 .
1(
#1240
0(
#1250
b111111 .
1(
#1260
0(
#1270
b1000000 .
1(
#1280
0(
#1290
b1000001 .
1(
#1300
0(
#1310
b1000010 .
1(
#1320
0(
#1330
b1000011 .
1(
#1340
0(
#1350
b1000100 .
1(
#1360
0(
#1370
b1000101 .
1(
#1380
0(
#1390
b1000110 .
1(
#1400
0(
#1410
b1000111 .
1(
#1420
0(
#1430
b1001000 .
1(
#1440
0(
#1450
b1001001 .
1(
#1460
0(
#1470
b1001010 .
1(
#1480
0(
#1490
b1001011 .
1(
#1500
0(
#1510
b1001100 .
1(
#1520
0(
#1530
b1001101 .
1(
#1540
0(
#1550
b1001110 .
1(
#1560
0(
#1570
b1001111 .
1(
#1580
0(
#1590
b1010000 .
1(
#1600
0(
#1610
b1010001 .
1(
#1620
0(
#1630
b1010010 .
1(
#1640
0(
#1650
b1010011 .
1(
#1660
0(
#1670
b1010100 .
1(
#1680
0(
#1690
b1010101 .
1(
#1700
0(
#1710
b1010110 .
1(
#1720
0(
#1730
b1010111 .
1(
#1740
0(
#1750
b1011000 .
1(
#1760
0(
#1770
b1011001 .
1(
#1780
0(
#1790
b1011010 .
1(
#1800
0(
#1810
b1011011 .
1(
#1820
0(
#1830
b1011100 .
1(
#1840
0(
#1850
b1011101 .
1(
#1860
0(
#1870
b1011110 .
1(
#1880
0(
#1890
b1011111 .
1(
#1900
0(
#1910
b1100000 .
1(
#1920
0(
#1930
b1100001 .
1(
#1940
0(
#1950
b1100010 .
1(
#1960
0(
#1970
b1100011 .
1(
#1980
0(
#1990
b1100100 .
1(
#2000
0(
#2010
b1100101 .
1(
#2020
0(
#2030
b1100110 .
1(
#2040
0(
#2050
b1100111 .
1(
#2060
0(
#2070
b1101000 .
1(
#2080
0(
#2090
b1101001 .
1(
#2100
0(
#2110
b1101010 .
1(
#2120
0(
#2130
b1101011 .
1(
#2140
0(
#2150
b1101100 .
1(
#2160
0(
#2170
b1101101 .
1(
#2180
0(
#2190
b1101110 .
1(
#2200
0(
#2210
b1101111 .
1(
#2220
0(
#2230
b1110000 .
1(
#2240
0(
#2250
b1110001 .
1(
#2260
0(
#2270
b1110010 .
1(
#2280
0(
#2290
b1110011 .
1(
#2300
0(
#2310
b1110100 .
1(
#2320
0(
#2330
b1110101 .
1(
#2340
0(
#2350
b1110110 .
1(
#2360
0(
#2370
b1110111 .
1(
#2380
0(
#2390
b1111000 .
1(
#2400
0(
0&
0)
#2410
1,
b0 .
1(
#2420
0(
1&
1)
#2430
b1 .
1(
#2440
0(
#2450
b10 .
1(
#2460
0(
#2470
b11 .
1(
#2480
0(
#2490
1'
1-
b100 .
1(
#2500
0'
0(
#2510
b101 .
1'
1(
#2520
0'
0(
#2530
b110 .
1'
1(
#2540
0'
0(
#2550
b111 .
1'
1(
#2560
0'
0(
#2570
b1000 .
1'
1(
#2580
0'
0(
#2590
b1001 .
1'
1(
#2600
0'
0(
#2610
b1010 .
1'
1(
#2620
0'
0(
#2630
b1011 .
1'
1(
#2640
0'
0(
#2650
b1100 .
1'
1(
#2660
0'
0(
#2670
b1101 .
1'
1(
#2680
0'
0(
#2690
b1110 .
1'
1(
#2700
0'
0(
#2710
b1111 .
1'
1(
#2720
0'
0(
#2730
b10000 .
1'
1(
#2740
0%
0$
0'
0(
#2750
b10001 .
1'
1(
#2760
1%
1$
0'
0(
#2770
1/
b10010 .
1'
1(
#2780
0'
0(
#2790
b10111010010 0
b10011 .
1'
b1 1
1#
1(
#2800
0'
0(
#2810
b10100 .
1'
1!
0#
1(
#2820
0'
0(
#2830
b10101 .
1'
b10 1
1#
1(
#2840
0'
0(
#2850
b10110 .
1'
0!
0#
1(
#2860
0'
0(
#2870
b10111 .
1'
b11 1
1#
1(
#2880
0'
0(
#2890
b11000 .
1'
0#
1(
#2900
0'
0(
#2910
b11001 .
1'
b100 1
1#
1(
#2920
0'
0(
#2930
b11010 .
1'
1!
0#
1(
#2940
0'
0(
#2950
b11011 .
1'
b101 1
1#
1(
#2960
0'
0(
#2970
b11100 .
1'
0!
0#
1(
#2980
0'
0(
#2990
b11101 .
1'
b110 1
1#
1(
#3000
0'
0(
#3010
b11110 .
1'
1!
0#
1(
#3020
0%
0$
0'
0(
#3030
b11111 .
1'
b111 1
1#
1(
#3040
1%
1$
0'
0(
#3050
b100000 .
1'
0#
1(
#3060
0'
0(
#3070
b100001 .
1'
b1000 1
1#
1(
#3080
0'
0(
#3090
b100010 .
1'
0#
1(
#3100
0'
0(
#3110
b100011 .
1'
b1001 1
1#
1(
#3120
0'
0(
#3130
b100100 .
1'
0!
0#
1(
#3140
0'
0(
#3150
b100101 .
1'
b1010 1
1#
1(
#3160
0'
0(
#3170
b100110 .
1'
1!
0#
1(
#3180
0'
0(
#3190
b100111 .
1'
b1011 1
1#
1(
#3200
0'
0(
#3210
b101000 .
1'
0!
0#
1(
#3220
0'
0(
#3230
b101001 .
1'
b1100 1
1#
1(
#3240
0'
0(
#3250
b101010 .
1'
x!
0#
1(
#3260
0'
0(
#3270
b101011 .
1'
b1101 1
1#
1(
#3280
0'
0(
#3290
b101100 .
1'
0#
1(
#3300
0%
0$
0'
0(
#3310
b101101 .
1'
b1110 1
1#
1(
#3320
1%
1$
0'
0(
#3330
b101110 .
1'
0#
1(
#3340
0'
0(
#3350
b101111 .
1'
b1111 1
1#
1(
#3360
0'
0(
#3370
b110000 .
1'
0#
1(
#3380
0'
0(
#3390
b110001 .
1'
b10000 1
1#
1(
#3400
0'
0(
#3410
b110010 .
1'
0#
1(
#3420
0'
0(
#3430
b110011 .
1'
b10001 1
1#
1(
#3440
0'
0(
#3450
b110100 .
1'
0#
1(
#3460
0'
0(
#3470
b110101 .
1'
b10010 1
1#
1(
#3480
0'
0(
#3490
b110110 .
1'
0#
1(
#3500
0'
0(
#3510
b110111 .
1'
b10011 1
1#
1(
#3520
0'
0(
#3530
b111000 .
1'
0#
1(
#3540
0'
0(
#3550
b111001 .
1'
b10100 1
1#
1(
#3560
0'
0(
#3570
b111010 .
1'
0#
1(
#3580
0%
0$
0'
0(
#3590
b111011 .
1'
b10101 1
1#
1(
#3600
1%
1$
0'
0(
#3610
b111100 .
1'
0#
1(
#3620
0'
0(
#3630
b111101 .
1'
b10110 1
1#
1(
#3640
0'
0(
#3650
b111110 .
1'
0#
1(
#3660
0'
0(
#3670
b111111 .
1'
b10111 1
1#
1(
#3680
0'
0(
#3690
0,
b1000000 .
0'
0#
1(
#3700
0(
#3710
b1000001 .
b11000 1
1#
1(
#3720
0(
#3730
b1000010 .
0#
1(
#3740
0(
#3750
b1000011 .
b11001 1
1#
1(
#3760
0(
#3770
b1000100 .
0#
1(
#3780
0(
#3790
b1000101 .
b11010 1
1#
1(
#3800
0(
#3810
b1000110 .
0#
1(
#3820
0(
#3830
b1000111 .
b11011 1
1#
1(
#3840
0(
#3850
b1001000 .
0#
1(
#3860
0(
#3870
b1001001 .
b11100 1
1#
1(
#3880
0(
#3890
b1001010 .
0#
1(
#3900
0(
#3910
b1001011 .
b11101 1
1#
1(
#3920
0(
#3930
b1001100 .
0#
1(
#3940
0(
#3950
b1001101 .
b11110 1
1#
1(
#3960
0(
#3970
b1001110 .
0#
1(
#3980
0(
#3990
b1001111 .
b11111 1
1#
1(
#4000
0(
#4010
b1010000 .
0#
1(
#4020
0(
#4030
b1010001 .
b0 1
1#
1(
#4040
0(
#4050
b1010010 .
0!
0#
1(
#4060
0(
#4070
b1010011 .
b1 1
1#
1(
#4080
0(
#4090
b1010100 .
1!
0#
1(
#4100
0(
#4110
b1010101 .
b10 1
1#
1(
#4120
0(
#4130
b1010110 .
0!
0#
1(
#4140
0(
#4150
b1010111 .
b11 1
1#
1(
#4160
0(
#4170
b1011000 .
0#
1(
#4180
0(
#4190
b1011001 .
b100 1
1#
1(
#4200
0(
#4210
b1011010 .
1!
0#
1(
#4220
0(
#4230
b1011011 .
b101 1
1#
1(
#4240
0(
#4250
b1011100 .
0!
0#
1(
#4260
0(
#4270
b1011101 .
b110 1
1#
1(
#4280
0(
#4290
b1011110 .
1!
0#
1(
#4300
0(
#4310
b1011111 .
b111 1
1#
1(
#4320
0(
#4330
b1100000 .
0#
1(
#4340
0(
#4350
b1100001 .
b1000 1
1#
1(
#4360
0(
#4370
b1100010 .
0#
1(
#4380
0(
#4390
b1100011 .
b1001 1
1#
1(
#4400
0(
#4410
b1100100 .
0!
0#
1(
#4420
0(
#4430
b1100101 .
b1010 1
1#
1(
#4440
0(
#4450
b1100110 .
1!
0#
1(
#4460
0(
#4470
b1100111 .
b1011 1
1#
1(
#4480
0(
#4490
b1101000 .
0!
0#
1(
#4500
0(
#4510
b1101001 .
b1100 1
1#
1(
#4520
0(
#4530
b1101010 .
x!
0#
1(
#4540
0(
#4550
b1101011 .
b1101 1
1#
1(
#4560
0(
#4570
b1101100 .
0#
1(
#4580
0(
#4590
b1101101 .
b1110 1
1#
1(
#4600
0(
#4610
b1101110 .
0#
1(
#4620
0(
#4630
b1101111 .
b1111 1
1#
1(
#4640
0(
#4650
b1110000 .
0#
1(
#4660
0(
#4670
b1110001 .
b10000 1
1#
1(
#4680
0(
#4690
b1110010 .
0#
1(
#4700
0(
#4710
b1110011 .
b10001 1
1#
1(
#4720
0(
#4730
b1110100 .
0#
1(
#4740
0(
#4750
b1110101 .
b10010 1
1#
1(
#4760
0(
#4770
b1110110 .
0#
1(
#4780
0(
#4790
b1110111 .
b10011 1
1#
1(
#4800
0(
#4810
b1111000 .
0#
1(
#4820
0(
0&
0)
#4830
1'
1,
b0 .
b10100 1
1#
1(
#4840
0'
0(
1&
1)
#4850
b1 .
1'
0#
1(
#4860
0'
0(
#4870
b10 .
1'
b10101 1
1#
1(
#4880
0'
0(
#4890
b11 .
1'
0#
1(
#4900
0'
0(
#4910
b100 .
1'
b10110 1
1#
1(
#4920
0'
0(
#4930
b101 .
1'
0#
1(
#4940
0'
0(
#4950
b110 .
1'
b10111 1
1#
1(
#4960
0'
0(
#4970
b111 .
1'
0#
1(
#4980
0'
0(
#4990
b1000 .
1'
b11000 1
1#
1(
#5000
0'
0(
#5010
b1001 .
1'
0#
1(
#5020
0'
0(
#5030
b1010 .
1'
b11001 1
1#
1(
#5040
0'
0(
#5050
b1011 .
1'
0#
1(
#5060
0'
0(
#5070
b1100 .
1'
b11010 1
1#
1(
#5080
0'
0(
#5090
b1101 .
1'
0#
1(
#5100
0'
0(
#5110
b1110 .
1'
b11011 1
1#
1(
#5120
0'
0(
#5130
b1111 .
1'
0#
1(
#5140
0'
0(
#5150
b10000 .
1'
b11100 1
1#
1(
#5160
0%
0$
0'
0(
#5170
b10001 .
1'
0#
1(
#5180
1%
1$
0'
0(
#5190
b10010 .
1'
b11101 1
1#
1(
#5200
0'
0(
#5210
b10011 .
1'
0#
1(
#5220
0'
0(
#5230
b10100 .
1'
b11110 1
1#
1(
#5240
0'
0(
#5250
b10101 .
1'
0#
1(
#5260
0'
0(
#5270
b10110 .
1'
b11111 1
1#
1(
#5280
0'
0(
#5290
b10111 .
1'
0#
1(
#5300
0'
0(
#5310
b11000 .
1'
b0 1
1#
1(
#5320
0'
0(
#5330
b11001 .
1'
0!
0#
1(
#5340
0'
0(
#5350
b11010 .
1'
b1 1
1#
1(
#5360
0'
0(
#5370
b11011 .
1'
1!
0#
1(
#5380
0'
0(
#5390
b11100 .
1'
b10 1
1#
1(
#5400
0'
0(
#5410
b11101 .
1'
0!
0#
1(
#5420
0'
0(
#5430
b11110 .
1'
b11 1
1#
1(
#5440
0%
0$
0'
0(
#5450
b11111 .
1'
0#
1(
#5460
1%
1$
0'
0(
#5470
b100000 .
1'
b100 1
1#
1(
#5480
0'
0(
#5490
b100001 .
1'
1!
0#
1(
#5500
0'
0(
#5510
b100010 .
1'
b101 1
1#
1(
#5520
0'
0(
#5530
b100011 .
1'
0!
0#
1(
#5540
0'
0(
#5550
b100100 .
1'
b110 1
1#
1(
#5560
0'
0(
#5570
b100101 .
1'
1!
0#
1(
#5580
0'
0(
#5590
b100110 .
1'
b111 1
1#
1(
#5600
0'
0(
#5610
b100111 .
1'
0#
1(
#5620
0'
0(
#5630
b101000 .
1'
b1000 1
1#
1(
#5640
0'
0(
#5650
b101001 .
1'
0#
1(
#5660
0'
0(
#5670
b101010 .
1'
b1001 1
1#
1(
#5680
0'
0(
#5690
b101011 .
1'
0!
0#
1(
#5700
0'
0(
#5710
b101100 .
1'
b1010 1
1#
1(
#5720
0%
0$
0'
0(
#5730
b101101 .
1'
1!
0#
1(
#5740
1%
1$
0'
0(
#5750
b101110 .
1'
b1011 1
1#
1(
#5760
0'
0(
#5770
b101111 .
1'
0!
0#
1(
#5780
0'
0(
#5790
b110000 .
1'
b1100 1
1#
1(
#5800
0'
0(
#5810
b110001 .
1'
x!
0#
1(
#5820
0'
0(
#5830
b110010 .
1'
b1101 1
1#
1(
#5840
0'
0(
#5850
b110011 .
1'
0#
1(
#5860
0'
0(
#5870
b110100 .
1'
b1110 1
1#
1(
#5880
0'
0(
#5890
b110101 .
1'
0#
1(
#5900
0'
0(
#5910
b110110 .
1'
b1111 1
1#
1(
#5920
0'
0(
#5930
b110111 .
1'
0#
1(
#5940
0'
0(
#5950
b111000 .
1'
b10000 1
1#
1(
#5960
0'
0(
#5970
b111001 .
1'
0#
1(
#5980
0'
0(
#5990
b111010 .
1'
b10001 1
1#
1(
#6000
0%
0$
0'
0(
#6010
b111011 .
1'
0#
1(
#6020
1%
1$
0'
0(
#6030
b111100 .
1'
b10010 1
1#
1(
#6040
0'
0(
#6050
b111101 .
1'
0#
1(
#6060
0'
0(
#6070
b111110 .
1'
b10011 1
1#
1(
#6080
0'
0(
#6090
b111111 .
1'
0#
1(
#6100
0'
0(
#6110
0,
b1000000 .
0'
b10100 1
1#
1(
#6120
0(
#6130
b1000001 .
0#
1(
#6140
0(
#6150
b1000010 .
b10101 1
1#
1(
#6160
0(
#6170
b1000011 .
0#
1(
#6180
0(
#6190
b1000100 .
b10110 1
1#
1(
#6200
0(
#6210
b1000101 .
0#
1(
#6220
0(
#6230
b1000110 .
b10111 1
1#
1(
#6240
0(
#6250
b1000111 .
0#
1(
#6260
0(
#6270
b1001000 .
b11000 1
1#
1(
#6280
0(
#6290
b1001001 .
0#
1(
#6300
0(
#6310
b1001010 .
b11001 1
1#
1(
#6320
0(
#6330
b1001011 .
0#
1(
#6340
0(
#6350
b1001100 .
b11010 1
1#
1(
#6360
0(
#6370
b1001101 .
0#
1(
#6380
0(
#6390
b1001110 .
b11011 1
1#
1(
#6400
0(
#6410
b1001111 .
0#
1(
#6420
0(
#6430
b1010000 .
b11100 1
1#
1(
#6440
0(
#6450
b1010001 .
0#
1(
#6460
0(
#6470
b1010010 .
b11101 1
1#
1(
#6480
0(
#6490
b1010011 .
0#
1(
#6500
0(
#6510
b1010100 .
b11110 1
1#
1(
#6520
0(
#6530
b1010101 .
0#
1(
#6540
0(
#6550
b1010110 .
b11111 1
1#
1(
#6560
0(
#6570
b1010111 .
0#
1(
#6580
0(
#6590
b1011000 .
b0 1
1#
1(
#6600
0(
#6610
b1011001 .
0!
0#
1(
#6620
0(
#6630
b1011010 .
b1 1
1#
1(
#6640
0(
#6650
b1011011 .
1!
0#
1(
#6660
0(
#6670
b1011100 .
b10 1
1#
1(
#6680
0(
#6690
b1011101 .
0!
0#
1(
#6700
0(
#6710
b1011110 .
b11 1
1#
1(
#6720
0(
#6730
b1011111 .
0#
1(
#6740
0(
#6750
b1100000 .
b100 1
1#
1(
#6760
0(
#6770
b1100001 .
1!
0#
1(
#6780
0(
#6790
b1100010 .
b101 1
1#
1(
#6800
0(
#6810
b1100011 .
0!
0#
1(
#6820
0(
#6830
b1100100 .
b110 1
1#
1(
#6840
0(
#6850
b1100101 .
1!
0#
1(
#6860
0(
#6870
b1100110 .
b111 1
1#
1(
#6880
0(
#6890
b1100111 .
0#
1(
#6900
0(
#6910
b1101000 .
b1000 1
1#
1(
#6920
0(
#6930
b1101001 .
0#
1(
#6940
0(
#6950
b1101010 .
b1001 1
1#
1(
#6960
0(
#6970
b1101011 .
0!
0#
1(
#6980
0(
#6990
b1101100 .
b1010 1
1#
1(
