FW/CPLDCodes/seq_seeker2.v
//Sequence Seeker, find the sequence  0110 including the overlap case

module seekseq2 (
    input clk,
    input rst,
    input x,

    output z
);
    parameter S0 = 2'b0, S1 = 2'b1, S2 = 2'b10, S3 = 2'b11;
    reg [1:0] present_state; reg z; reg [1:0] next_state;
   
   // F/F
   always @(posedge clk or posedge rst) begin
       present_state <= next_state;
       if(rst == 1'b1) begin
            next_state = S0;
        end
   end

   //output logic z
    always @(x, present_state) begin
        z = (&present_state)&(~x);
    end
    

    //next stage stage
    always @(x or present_state ) begin
            case(present_state)
                S0: begin
                    next_state = x?S0:S1;
                end
                S1: begin
                    next_state = x?S2:S1;
                end
                S2: begin
                    next_state = x?S3:S1;
                end
                S3: begin
                    next_state = x?S0:S1;
                end
            endcase
    end
endmodule

FW/CPLDCodes/seq_seeker.v
//Sequence Seeker, find the sequence  0110 including the overlap case

module seekseq (
    input clk,
    input rst,
    input x,

    output z
);
    parameter S0 = 2'b0, S1 = 2'b1, S2 = 2'b10, S3 = 2'b11;
    reg [1:0] state; reg z;
   

    always @(posedge clk or posedge rst) begin
        if(rst == 1'b1) begin
            state <= S0;
        end
        else begin
            z = (&state)&(~x);
            case(state)
                S0: begin
                    state = x?S0:S1;
                end
                S1: begin
                    state = x?S2:S1;
                end
                S2: begin
                    state = x?S3:S1;
                end
                S3: begin
                    state = x?S0:S1;
                end
            endcase
        end
    end
endmodule

FW/CPLDCodes/testbench_seq.v
`timescale 100ns/1ns
//TestBench for AD7864
module testbench_seq;
    reg clk,x,reset;
    wire z1,z2;
    
    seekseq DUT(clk, reset, x, z1);
    seekseq2 DUT2(clk, reset, x, z2);
    
    initial begin
        $dumpfile("sequence.vcd");$dumpvars(0,testbench_seq);
        clk = 1'b0;
        reset = 1'b1;
        #15 reset = 1'b0;
    end

    always
        #5 clk = ~clk;
    
    always begin
        #12 x = 0; #10 x = 0; #10 x = 1; #10 x = 1;
        #10 x = 0; #10 x = 1; #10 x = 1; #10 x = 0;
        #10 x = 0; #10 x = 1; #10 x = 1; #10 x = 0;
        #10 $finish;
    end

    
endmodule

FW/CPLDCodes/sequence.vcd
$date
	Sat Apr  3 23:58:10 2021
$end
$version
	Icarus Verilog
$end
$timescale
	1ns
$end
$scope module testbench_seq $end
$var wire 1 ! z2 $end
$var wire 1 " z1 $end
$var reg 1 # clk $end
$var reg 1 $ reset $end
$var reg 1 % x $end
$scope module DUT $end
$var wire 1 # clk $end
$var wire 1 $ rst $end
$var wire 1 % x $end
$var reg 2 & state [1:0] $end
$var reg 1 " z $end
$upscope $end
$scope module DUT2 $end
$var wire 1 # clk $end
$var wire 1 $ rst $end
$var wire 1 % x $end
$var reg 2 ' next_state [1:0] $end
$var reg 2 ( present_state [1:0] $end
$var reg 1 ! z $end
$upscope $end
$upscope $end
$enddefinitions $end
#0
$dumpvars
bx (
b0 '
b0 &
x%
1$
0#
x"
x!
$end
#500
b0x '
0!
b0 (
1#
#1000
0#
#1200
b1 '
0%
#1500
b1 (
b1 &
0"
1#
0$
#2000
0#
#2500
1#
#3000
0#
#3200
b10 '
1%
#3500
b11 '
b10 (
b10 &
1#
#4000
0#
#4500
b0 '
b11 (
b11 &
1#
#5000
0#
#5200
b1 '
1!
0%
#5500
0!
b1 (
b1 &
1"
1#
#6000
0#
#6200
b10 '
1%
#6500
b11 '
b10 (
b10 &
0"
1#
#7000
0#
#7500
b0 '
b11 (
b11 &
1#
#8000
0#
#8200
1!
b1 '
0%
#8500
0!
b1 (
b1 &
1"
1#
#9000
0#
#9500
0"
1#
#10000
0#
#10200
b10 '
1%
#10500
b11 '
b10 (
b10 &
1#
#11000
0#
#11500
b0 '
b11 (
b11 &
1#
#12000
0#
#12200
b1 '
1!
0%
#12500
0!
b1 (
b1 &
1"
1#
